odoo/addons/partner_label/README.rst
odoo/addons/partner_label/__init__.py
odoo/addons/partner_label/__manifest__.py
odoo/addons/partner_label/i18n/cs_CZ.po
odoo/addons/partner_label/i18n/da.po
odoo/addons/partner_label/i18n/de.po
odoo/addons/partner_label/i18n/es.po
odoo/addons/partner_label/i18n/fr.po
odoo/addons/partner_label/i18n/hr.po
odoo/addons/partner_label/i18n/hr_HR.po
odoo/addons/partner_label/i18n/it.po
odoo/addons/partner_label/i18n/nl_NL.po
odoo/addons/partner_label/i18n/partner_label.pot
odoo/addons/partner_label/i18n/pt_BR.po
odoo/addons/partner_label/i18n/pt_PT.po
odoo/addons/partner_label/i18n/sl.po
odoo/addons/partner_label/models/__init__.py
odoo/addons/partner_label/models/res_company.py
odoo/addons/partner_label/models/res_config_settings.py
odoo/addons/partner_label/readme/CONFIGURE.rst
odoo/addons/partner_label/readme/CONTRIBUTERS.rst
odoo/addons/partner_label/readme/USAGE.rst
odoo/addons/partner_label/reports/res_partner.xml
odoo/addons/partner_label/static/description/icon.png
odoo/addons/partner_label/tests/__init__.py
odoo/addons/partner_label/tests/test_partner_label.py
odoo/addons/partner_label/views/base_config_settings.xml
odoo13_addon_partner_label-13.0.1.0.1.dist-info/METADATA
odoo13_addon_partner_label-13.0.1.0.1.dist-info/WHEEL
odoo13_addon_partner_label-13.0.1.0.1.dist-info/top_level.txt
odoo13_addon_partner_label-13.0.1.0.1.dist-info/RECORD
